CurrencyExchange/__init__.py
CurrencyExchange/currency_exchange.py
CurrencyExchange/logger.py
CurrencyExchange/menu.py
tests/__init__.py
tests/test_currency.py
currency_exchange-1.0.0.dist-info/METADATA
currency_exchange-1.0.0.dist-info/WHEEL
currency_exchange-1.0.0.dist-info/entry_points.txt
currency_exchange-1.0.0.dist-info/top_level.txt
currency_exchange-1.0.0.dist-info/RECORD
